{
  "jsonData": [
    {
      "담보명": "치수치료비",
      "가입금액": "3",
      "KB손해보험": 3213,
      "삼성화재": 2943,
      "현대해상화재": 1758,
      "DB손해보험": 2295,
      "메리츠화재": 1548,
      "한화손해보험": 1677
    },
    {
      "담보명": "치아보철치료비",
      "가입금액": "100",
      "KB손해보험": 31940,
      "삼성화재": 37590,
      "현대해상화재": 41810,
      "DB손해보험": 44790,
      "메리츠화재": 55612,
      "한화손해보험": 61230
    },
    {
      "담보명": "치아보존치료비",
      "가입금액": "10",
      "KB손해보험": 10372,
      "삼성화재": 9508,
      "현대해상화재": 10315,
      "DB손해보험": 11140,
      "메리츠화재": 11388,
      "한화손해보험": 11370
    },
    {
      "담보명": "치주질환치료비",
      "가입금액": "2",
      "KB손해보험": 800,
      "삼성화재": 684,
      "현대해상화재": 768,
      "DB손해보험": 670,
      "메리츠화재": 398,
      "한화손해보험": 716
    },
    {
      "담보명": "영구치상실치료비",
      "가입금액": "5",
      "KB손해보험": 1815,
      "삼성화재": 1883,
      "현대해상화재": 3360,
      "DB손해보험": 2570,
      "메리츠화재": 6237,
      "한화손해보험": 3115
    },
    {
      "담보명": "특정치석제거(스케일링)치료비",
      "가입금액": "1",
      "KB손해보험": 684,
      "삼성화재": 590,
      "현대해상화재": 590,
      "DB손해보험": 569,
      "메리츠화재": 560,
      "한화손해보험": 581
    },
    {
      "담보명": "X-Ray및파노라마치아촬영비",
      "가입금액": "1",
      "KB손해보험": 1450,
      "삼성화재": 1298,
      "현대해상화재": 1150,
      "DB손해보험": 1235,
      "메리츠화재": 1204,
      "한화손해보험": 1371
    },
    {
      "담보명": "발치치료비",
      "가입금액": "4",
      "KB손해보험": 364,
      "삼성화재": 360,
      "현대해상화재": 460,
      "DB손해보험": 316,
      "메리츠화재": 404,
      "한화손해보험": 356
    },
    {
      "담보명": "특정임플란트치조골이식술치료비",
      "가입금액": "10",
      "KB손해보험": 1503,
      "삼성화재": 1548,
      "현대해상화재": 1745,
      "DB손해보험": 1914,
      "메리츠화재": 2253,
      "한화손해보험": 2293
    },
    {
      "담보명": "합계",
      "가입금액": "",
      "KB손해보험": 52141,
      "삼성화재": 56404,
      "현대해상화재": 61956,
      "DB손해보험": 65499,
      "메리츠화재": 79604,
      "한화손해보험": 82709
    }
  ],
  "productData": {
    "KB손해보험": "무)The건강한치아보험(25.04)",
    "삼성화재": "무)치아보험 덴탈파트너(2404.10)",
    "현대해상화재": "무)밝게웃는얼굴치아보험(연만기갱신형)(Hi2504)",
    "DB손해보험": "무)참좋은치아사랑보험2504",
    "메리츠화재": "무)메리츠치아보험이목구비2504",
    "한화손해보험": "무)하얀미소플러스치아보험Ⅱ2504"
  }
}